setup.cfg
setup.py
django_snailtracker/__init__.py
django_snailtracker/admin.py
django_snailtracker/constants.py
django_snailtracker/exceptions.py
django_snailtracker/helpers.py
django_snailtracker/models.py
django_snailtracker/serializer.py
django_snailtracker/sites.py
django_snailtracker/tasks.py
django_snailtracker/urls.py
django_snailtracker/utils.py
django_snailtracker/views.py
django_snailtracker.egg-info/PKG-INFO
django_snailtracker.egg-info/SOURCES.txt
django_snailtracker.egg-info/dependency_links.txt
django_snailtracker.egg-info/entry_points.txt
django_snailtracker.egg-info/not-zip-safe
django_snailtracker.egg-info/top_level.txt
django_snailtracker/migrations/0001_initial.py
django_snailtracker/migrations/0002_auto__add_objectlock__add_unique_objectlock_table_object_pk.py
django_snailtracker/migrations/__init__.py
django_snailtracker/tests/__init__.py