Metadata-Version: 1.0
Name: django-snailtracker
Version: 0.6.7
Summary: Track history on django models
Home-page: UNKNOWN
Author: Kyle Terry
Author-email: kyle@kyleterry.com
License: New BSD License
Keywords: django model-history-tracking
Platform: UNKNOWN
